{
	"companyName": "Национальная Управляющая компания",
	"title": "sqwqwq11111111111111s",
	"news": [
		{
			"date": "10 февраля 2016",
			"title": "Изменение фирменного наименования, места нахождения, номеров телефонов и факса",
			"shortText": "",
			"url": "#"
		},
		{
			"date": "03 февраля 2016",
			"title": "По итогам открытого конкурса ЗАО «НУК» будут переданы в доверительное управление",
			"shortText": "",
			"url": "#"
		},
		{
			"date": "10 февраля 2016",
			"title": "Изменение фирменного наименования, места нахождения, номеров телефонов и факса",
			"shortText": "",
			"url": "#"
		},
		{
			"date": "03 февраля 2016",
			"title": "По итогам открытого конкурса ЗАО «НУК» будут переданы в доверительное управление",
			"shortText": "",
			"url": "#"
		}
	],
	"asideMenu": [
		{
			"caption": "Паевые фонды",
			"type": "list",
			"items": [
				{
					"caption": "ОПИФ",
					"href": "#"
				},
				{
					"caption": "ЗПИФ",
					"href": "#"
				},
				{
					"caption": "ИПИФ",
					"href": "#"
				},
				{
					"caption": "Отчетность и документы Специализированного депозитария",
					"href": "#"
				}
			]
		},
		{
			"caption": "Доверительное управление",
			"type": "link",
			"url": "#"
		},
		{
			"caption": "Управление целевым капиталом",
			"type": "link",
			"url": "#"
		},
		{
			"caption": "Управление страховыми резервами",
			"type": "link",
			"url": "#"
		},
		{
			"caption": "Управление компенсационным фондом СРО",
			"type": "link",
			"url": "#"
		},
		{
			"caption": "Управление активами НПФ",
			"type": "link",
			"url": "#"
		}
	]
}